human_keyboard/__init__.py
human_keyboard/human_keyboard.py
human_keyboard-0.1.0.dist-info/LICENSE
human_keyboard-0.1.0.dist-info/METADATA
human_keyboard-0.1.0.dist-info/WHEEL
human_keyboard-0.1.0.dist-info/top_level.txt
human_keyboard-0.1.0.dist-info/RECORD
