Metadata-Version: 2.1
Name: human-keyboard
Version: 0.1.0
Summary: Simulates human typing behavior with realistic timing and errors.
Home-page: https://github.com/luishacm/human-keyboard
Author: @luishacm
Author-email: tvsala19112020@gmail.com
Classifier: Programming Language :: Python :: 3
Classifier: Operating System :: OS Independent
License-File: LICENSE
Requires-Dist: numpy
Requires-Dist: keyboard
